{
  "parent": "dungeons_plus:adventure/find_bigger_dungeon",
  "display": {
    "icon": {
      "item": "minecraft:packed_ice"
    },
    "title": {
      "translate": "advancements.dungeons_plus.adventure.find_snowy_temple"
    },
    "description": {
      "translate": "advancements.dungeons_plus.adventure.find_snowy_temple.desc"
    },
    "frame": "goal",
    "show_toast": true,
    "announce_to_chat": true,
    "hidden": false
  },
  "criteria": {
    "enter_structure": {
      "trigger": "minecraft:location",
      "conditions": {
        "location": {
          "feature": "dungeons_plus:snowy_temple"
        }
      }
    }
  },
  "requirements": [
    [
      "enter_structure"
    ]
  ]
}